fastmcp_extensions/__init__.py
fastmcp_extensions/_middleware.py
fastmcp_extensions/annotations.py
fastmcp_extensions/decorators.py
fastmcp_extensions/prompts.py
fastmcp_extensions/py.typed
fastmcp_extensions/registration.py
fastmcp_extensions/server.py
fastmcp_extensions/server_config.py
fastmcp_extensions/tool_filters.py
fastmcp_extensions/utils/__init__.py
fastmcp_extensions/utils/_http.py
fastmcp_extensions/utils/describe_server.py
fastmcp_extensions/utils/test_tool.py
fastmcp_extensions-0.2.0.dist-info/METADATA
fastmcp_extensions-0.2.0.dist-info/WHEEL
fastmcp_extensions-0.2.0.dist-info/licenses/LICENSE
fastmcp_extensions-0.2.0.dist-info/RECORD
