Metadata-Version: 2.4
Name: fastmcp-extensions
Version: 0.2.0
Summary: Unofficial extension library for FastMCP 2.0 with patterns, practices, and utilities
Project-URL: Homepage, https://github.com/airbytehq/fastmcp-extensions
Project-URL: Repository, https://github.com/airbytehq/fastmcp-extensions
Project-URL: Documentation, https://github.com/airbytehq/fastmcp-extensions#readme
Author-email: Airbyte <contact@airbyte.io>
License:                                  Apache License
License-File: LICENSE
Keywords: extensions,fastmcp,mcp,model-context-protocol,utilities
Classifier: Development Status :: 4 - Beta
Classifier: Intended Audience :: Developers
Classifier: License :: OSI Approved :: MIT License
Classifier: Programming Language :: Python :: 3
Classifier: Programming Language :: Python :: 3.10
Classifier: Programming Language :: Python :: 3.11
Classifier: Programming Language :: Python :: 3.12
Classifier: Programming Language :: Python :: 3.13
Requires-Python: >=3.10
Requires-Dist: fastmcp<3.0,>=2.2.7
Provides-Extra: dev
Requires-Dist: deptry>=0.12.0; extra == 'dev'
Requires-Dist: mypy>=1.8.0; extra == 'dev'
Requires-Dist: poethepoet>=0.24.0; extra == 'dev'
Requires-Dist: pytest-asyncio>=0.23.0; extra == 'dev'
Requires-Dist: pytest-cov>=4.0; extra == 'dev'
Requires-Dist: pytest>=7.0; extra == 'dev'
Requires-Dist: ruff>=0.1.0; extra == 'dev'
